{
  "id": "glolo_v_intr_001",
  "headword": {
    "roman": "glolo",
    "coral": "holo",
    "ipa": ""
  },
  "pos": "verb",
  "gloss_de": [
    "gehen",
    "sich fortbewegen (zielgerichtet)"
  ],
  "grammar": {
    "conjugation_class": "standard",
    "valency": "intransitive"
  },
  "meta": {
    "status": "canonical",
    "tags": [
      "verb",
      "movement"
    ]
  },
  "korallisch": "holo",
  "inflection": {
    "present": {
      "type": "standard",
      "tense": "present",
      "forms": {
        "1sg": {
          "roman": "glolo",
          "coral": "holo"
        },
        "2sg": {
          "roman": "gloloi",
          "coral": "holoi"
        },
        "3sg": {
          "roman": "gloloie",
          "coral": "holoj"
        },
        "1pl": {
          "roman": "gloloh",
          "coral": "holö"
        },
        "2pl": {
          "roman": "glolohi",
          "coral": "holöi"
        },
        "3pl": {
          "roman": "glolohie",
          "coral": "holöj"
        }
      }
    }
  }
}